bolts.json
cq_queryabolt.py
nuts.json
cq_queryabolt-0.1.2.dist-info/LICENSE
cq_queryabolt-0.1.2.dist-info/METADATA
cq_queryabolt-0.1.2.dist-info/WHEEL
cq_queryabolt-0.1.2.dist-info/RECORD
